awscm_proxy/__init__.py
awscm_proxy/bidirectional-proxy.yaml
awscm_proxy/proxy.py
awscm_proxy/unidirectional-proxy.yaml
awscm_proxy-0.2.1.dist-info/entry_points.txt
awscm_proxy-0.2.1.dist-info/licenses/AUTHORS.rst
awscm_proxy-0.2.1.dist-info/licenses/LICENSE.txt
awscm_proxy-0.2.1.dist-info/WHEEL
awscm_proxy-0.2.1.dist-info/METADATA
awscm_proxy-0.2.1.dist-info/RECORD
