Metadata-Version: 2.4
Name: awscm-proxy
Version: 0.2.1
Summary: A cheap, secure, and straightforward serverless localhost proxy
Author: Aryeh Leib Taurog
Requires-Python: >=3.12
License-Expression: MIT
Classifier: Development Status :: 4 - Beta
Classifier: Environment :: Console
Classifier: Environment :: Web Environment
Classifier: Intended Audience :: Developers
Classifier: Programming Language :: Python :: 3
Classifier: Topic :: Internet :: Proxy Servers
License-File: AUTHORS.rst
License-File: LICENSE.txt
Requires-Dist: boto3>=1.40.23
Requires-Dist: mitmproxy>=12.2.0
Requires-Dist: requests>=2.32.5
Project-URL: documentation, https://awscm-proxy.readthedocs.io
Project-URL: issues, https://github.com/causematch/awscm-proxy/issues
Project-URL: repository, https://github.com/causematch/awscm-proxy
